<?xml version="1.0" encoding="utf-8" ?><dwsync><file name="american.html" local="-4360197644383944704" remote="-4356057086530953880" testing="0" /><file name="cdrom.html" local="-4360197610024206336" remote="-4356057086530953880" testing="0" /><file name="corporate.html" local="-4360197579959435264" remote="-4356057086530953880" testing="0" /><file name="djstyle.html" local="-4360197549894664192" remote="-4356057086530953880" testing="0" /><file name="informative.html" local="-4360197352326168576" remote="-4356057086530953880" testing="0" /><file name="medical.html" local="-4360197313671462912" remote="-4356057086530953880" testing="0" /><file name="radioad.html" local="-4360197287901659136" remote="-4356057086530953880" testing="0" /><file name="softread.html" local="-4360197262131855360" remote="-4356057086530953880" testing="0" /></dwsync>